karaage/.gitignore
karaage/__init__.py
karaage/__main__.py
karaage/apps.py
karaage/backends.py
karaage/cli.py
karaage/common/__init__.py
karaage/common/aaf_rapid_connect.py
karaage/common/constants.py
karaage/common/context_processors.py
karaage/common/create_update.py
karaage/common/decorators.py
karaage/common/emails.py
karaage/common/forms.py
karaage/common/models.py
karaage/common/passwords.py
karaage/common/simple.py
karaage/common/tables.py
karaage/common/trace.py
karaage/common/views/__init__.py
karaage/common/views/common.py
karaage/common/views/profile.py
karaage/conf/__init__.py
karaage/conf/defaults.py
karaage/conf/process.py
karaage/conf/settings.py
karaage/conf/urls.py
karaage/datastores/__init__.py
karaage/datastores/base.py
karaage/datastores/dummy.py
karaage/datastores/ldap.py
karaage/datastores/ldap_schemas.py
karaage/datastores/mam.py
karaage/datastores/slurm.py
karaage/emails/__init__.py
karaage/emails/forms.py
karaage/emails/models.py
karaage/emails/urls.py
karaage/emails/views.py
karaage/fixtures/test_karaage.json
karaage/institutes/__init__.py
karaage/institutes/forms.py
karaage/institutes/lookups.py
karaage/institutes/managers.py
karaage/institutes/models.py
karaage/institutes/tables.py
karaage/institutes/urls.py
karaage/institutes/views.py
karaage/logging.py
karaage/machines/__init__.py
karaage/machines/forms.py
karaage/machines/management.py
karaage/machines/managers.py
karaage/machines/models.py
karaage/machines/tables.py
karaage/machines/urls/__init__.py
karaage/machines/urls/accounts.py
karaage/machines/urls/machines.py
karaage/machines/views/__init__.py
karaage/machines/views/accounts.py
karaage/machines/views/machines.py
karaage/management/__init__.py
karaage/management/commands/__init__.py
karaage/management/commands/change_pid.py
karaage/management/commands/change_username.py
karaage/management/commands/changepassword.py
karaage/management/commands/daily_cleanup.py
karaage/management/commands/import_csv_users.py
karaage-6.3.1.dist-info/AUTHORS.txt
karaage-6.3.1.dist-info/COPYING.txt
karaage-6.3.1.dist-info/METADATA
karaage-6.3.1.dist-info/WHEEL
karaage-6.3.1.dist-info/entry_points.txt
karaage-6.3.1.dist-info/RECORD
