Metadata-Version: 2.3
Name: karaage
Version: 6.3.1
Summary: Web application to manage a HP cluster
License: GPL3+
Author: Brian May
Author-email: brian@linuxpenguins.xyz
Requires-Python: >=3.10,<4.0
Classifier: Development Status :: 5 - Production/Stable
Classifier: Intended Audience :: Developers
Classifier: Intended Audience :: System Administrators
Classifier: License :: OSI Approved :: GNU General Public License v3 or later (GPLv3+)
Classifier: License :: Other/Proprietary License
Classifier: Operating System :: OS Independent
Classifier: Programming Language :: Python :: 3
Classifier: Programming Language :: Python :: 3.10
Classifier: Programming Language :: Python :: 3.11
Classifier: Programming Language :: Python :: 3.12
Classifier: Programming Language :: Python :: 3.13
Classifier: Programming Language :: Python :: 3.8
Provides-Extra: docs
Requires-Dist: Django (>=4.1.2,<5.2.0)
Requires-Dist: bcrypt
Requires-Dist: cracklib
Requires-Dist: cssmin
Requires-Dist: django-ajax-selects
Requires-Dist: django-environ
Requires-Dist: django-filter
Requires-Dist: django-simple-captcha
Requires-Dist: django-tables2
Requires-Dist: django-tracking-model (>=0.1.5,<0.2.0)
Requires-Dist: furo ; extra == "docs"
Requires-Dist: gunicorn
Requires-Dist: jsmin (>=3.0.1,<4.0.0)
Requires-Dist: ldap3
Requires-Dist: mysqlclient
Requires-Dist: psycopg2-binary
Requires-Dist: pyjwt
Requires-Dist: python-alogger
Requires-Dist: python-tldap
Requires-Dist: sentry-sdk
Requires-Dist: six
Requires-Dist: sphinx ; extra == "docs"
Requires-Dist: whitenoise
Project-URL: Homepage, https://github.com/Karaage-Cluster/django/
